pitonio/__init__.py
pitonio-0.2.0.dist-info/licenses/LICENSE
pitonio-0.2.0.dist-info/METADATA
pitonio-0.2.0.dist-info/WHEEL
pitonio-0.2.0.dist-info/top_level.txt
pitonio-0.2.0.dist-info/RECORD
