Metadata-Version: 2.4
Name: pitonio
Version: 0.2.0
Summary: Python traduzido para Português pra facilitar
Home-page: https://github.com/aaaa560/Pitonio
Author: Decaptado
Author-email: Decaptado <naaaooo1939@gmail.com>
License: MIT
Project-URL: homepage, https://github.com/aaaa560/Pitonio
Keywords: python,português,tradução,pt-br
Classifier: Programming Language :: Python :: 3
Classifier: License :: OSI Approved :: MIT License
Classifier: Operating System :: OS Independent
Requires-Python: >=3.7
License-File: LICENSE
Dynamic: author
Dynamic: home-page
Dynamic: license-file
Dynamic: requires-python
